renxianqi/__init__.py
renxianqi/diff.py
renxianqi/localdata_loader.py
renxianqi/main.py
renxianqi/menu_setting.py
renxianqi/name_checker.py
renxianqi/name_checker2.py
renxianqi/name_parser.py
renxianqi/pinyin_sort.py
renxianqi/pip_trigger.py
renxianqi/setting.py
renxianqi/shortcut.py
renxianqi/ui/__init__.py
renxianqi/ui/menu_setting.py
renxianqi/ui/name_checker.py
tests/__init__.py
tests/diff_test.py
tests/name_parser_test.py
tests/pinyin_sort_test.py
tests/test_main.py
qingdian-1.0.12.dist-info/LICENSE
qingdian-1.0.12.dist-info/METADATA
qingdian-1.0.12.dist-info/WHEEL
qingdian-1.0.12.dist-info/entry_points.txt
qingdian-1.0.12.dist-info/top_level.txt
qingdian-1.0.12.dist-info/RECORD
